[
  {
    "name": "Love Unicorn",
    "slug": "love_unicorn",
    "category": "Love & Romance",
    "image": "/cards/unicorn-love.jpg",
    "createdAt": "2025-10-08T10:00:00Z",
    "views": 235,
    "sales": 42,
    "reviews": [5, 4, 5, 5, 4]
  },
  {
    "name": "Birthday Balloons",
    "slug": "birthday_balloons",
    "category": "Birthdays",
    "image": "/cards/birthday-balloons.jpg",
    "createdAt": "2025-10-07T08:00:00Z",
    "views": 187,
    "sales": 31,
    "reviews": [5, 5, 5, 4, 5, 4]
  },
  {
    "name": "Motivation Sunrise",
    "slug": "motivation_sunrise",
    "category": "Emotions & Motivation",
    "image": "/cards/motivation-sunrise.jpg",
    "createdAt": "2025-10-06T14:00:00Z",
    "views": 320,
    "sales": 18,
    "reviews": [4, 4, 5, 5, 5]
  }
]
